animestreamer/__init__.py
animestreamer/config.json
animestreamer/main.py
animestreamer/streamer.py
animestreamer/widgets/__init__.py
animestreamer/widgets/_custom_footer.py
animestreamer/widgets/_custom_header.py
animestreamer/widgets/_custom_widget.py
animestreamer/widgets/_help.py
animestreamer/widgets/_path_input.py
animestreamer/widgets/_sort.py
animestreamer/widgets/_torrent_input.py
animestreamer/widgets/_torrent_results.py
animestreamer-0.2.dist-info/LICENSE
animestreamer-0.2.dist-info/METADATA
animestreamer-0.2.dist-info/WHEEL
animestreamer-0.2.dist-info/entry_points.txt
animestreamer-0.2.dist-info/top_level.txt
animestreamer-0.2.dist-info/RECORD
