Metadata-Version: 2.1
Name: animestreamer
Version: 0.2
Summary: TUI for streaming NyaaPy torrents with WebTorrent
Home-page: https://github.com/YelovSK/AnimeStreamer-CLI
Author: Yelov
License: Apache License 2.0
Platform: UNKNOWN
Requires-Python: >=3.7
License-File: LICENSE
Requires-Dist: NyaaPy
Requires-Dist: rich
Requires-Dist: textual
Requires-Dist: textual-inputs
Requires-Dist: appdirs
Requires-Dist: anitopy
